jax_ai_stack/__init__.py
jax_ai_stack-2025.9.3.dist-info/licenses/LICENSE
jax_ai_stack-2025.9.3.dist-info/METADATA
jax_ai_stack-2025.9.3.dist-info/WHEEL
jax_ai_stack-2025.9.3.dist-info/top_level.txt
jax_ai_stack-2025.9.3.dist-info/RECORD
