Metadata-Version: 2.4
Name: jax-ai-stack
Version: 2025.9.3
Author-email: jax-ai-stack authors <jax-dev+jax-ai-stack@google.com>
License: 
Project-URL: homepage, https://github.com/jax-ml/jax_-ai-stack
Project-URL: repository, https://github.com/jax-ml/jax-ai-stack
Classifier: Programming Language :: Python :: 3
Classifier: Programming Language :: Python :: 3 :: Only
Classifier: License :: OSI Approved :: Apache Software License
Classifier: Intended Audience :: Science/Research
License-File: LICENSE
Requires-Dist: chex==0.1.90
Requires-Dist: grain==0.2.12
Requires-Dist: jax==0.7.0
Requires-Dist: flax==0.11.1
Requires-Dist: ml_dtypes==0.5.3
Requires-Dist: optax==0.2.5
Requires-Dist: orbax-checkpoint==0.11.23
Requires-Dist: orbax-export==0.0.6
Provides-Extra: dev
Requires-Dist: pytest; extra == "dev"
Requires-Dist: pytest-xdist; extra == "dev"
Provides-Extra: tfds
Requires-Dist: tensorflow==2.20.0; extra == "tfds"
Requires-Dist: tensorflow_datasets==4.9.9; extra == "tfds"
Provides-Extra: grain
Dynamic: license-file
